{
  "type": "minecraft:crafting_shapeless",
  "ingredients": [
    {
      "tag": "forge:beef/cooked"
    },
    {
      "tag": "forge:beef/cooked"
    },
    {
      "tag": "forge:beef/cooked"
    },
    {
      "tag": "forge:beef/cooked"
    },
    {
      "tag": "forge:beef/cooked"
    },
    {
      "tag": "forge:beef/cooked"
    },
    {
      "tag": "forge:beef/cooked"
    },
    {
      "tag": "forge:beef/cooked"
    },
    {
      "tag": "forge:beef/cooked"
    }
  ],
  "result": {
    "item": "butchercraft:cooked_beef_block_item"
  }
}